[
    {
        "id": 9,
        "title": "dfbdfbdfb",
        "content": "df",
        "created": "2025-10-29 11:03:57",
        "updated": "2025-10-29 11:03:57"
    },
    {
        "id": 10,
        "title": "dvdv",
        "content": "dv",
        "created": "2025-10-29 11:04:14",
        "updated": "2025-10-29 11:04:14"
    },
    {
        "id": 11,
        "title": "dvdv",
        "content": "d ",
        "created": "2025-10-29 11:04:20",
        "updated": "2025-10-29 11:04:20"
    },
    {
        "id": 13,
        "title": "а",
        "content": "аи",
        "created": "2025-10-29 11:05:33",
        "updated": "2025-10-29 11:05:33"
    },
    {
        "id": 14,
        "title": "а",
        "content": "а",
        "created": "2025-10-29 11:06:34",
        "updated": "2025-10-29 11:06:34"
    },
    {
        "id": 15,
        "title": "ави",
        "content": "а",
        "created": "2025-10-29 11:06:46",
        "updated": "2025-10-29 11:06:46"
    },
    {
        "id": 16,
        "title": "вмвмв",
        "content": "в",
        "created": "2025-10-29 11:08:32",
        "updated": "2025-10-29 11:08:32"
    },
    {
        "id": 17,
        "title": "ваи",
        "content": "в",
        "created": "2025-10-29 11:08:39",
        "updated": "2025-10-29 11:08:39"
    },
    {
        "id": 18,
        "title": "ва",
        "content": "в\r\n\r\n\r\n",
        "created": "2025-10-29 11:09:05",
        "updated": "2025-10-29 11:09:05"
    },
    {
        "id": 19,
        "title": "с",
        "content": "с",
        "created": "2025-10-29 11:09:10",
        "updated": "2025-10-29 11:09:10"
    },
    {
        "id": 20,
        "title": "в",
        "content": "в",
        "created": "2025-10-29 11:11:49",
        "updated": "2025-10-29 11:11:49"
    },
    {
        "id": 21,
        "title": "ваива",
        "content": "ваи",
        "created": "2025-10-29 11:11:56",
        "updated": "2025-10-29 11:11:56"
    },
    {
        "id": 22,
        "title": "вмвмв",
        "content": "ваи",
        "created": "2025-10-29 11:12:01",
        "updated": "2025-10-29 11:12:01"
    },
    {
        "id": 23,
        "title": "вмвмваи",
        "content": "ваи",
        "created": "2025-10-29 11:12:09",
        "updated": "2025-10-29 11:12:09"
    },
    {
        "id": 24,
        "title": "Я создал свой сайт!",
        "content": "Ура!",
        "created": "2025-10-29 11:23:31",
        "updated": "2025-10-29 11:23:31"
    },
    {
        "id": 26,
        "title": "d",
        "content": "\r\n",
        "created": "2025-10-29 12:14:12",
        "updated": "2025-10-29 12:14:12"
    },
    {
        "id": 27,
        "title": "d",
        "content": "ehehehehehe",
        "created": "2025-10-29 12:14:21",
        "updated": "2025-10-29 12:14:21"
    },
    {
        "id": 28,
        "title": " ",
        "content": "f ",
        "created": "2025-10-29 12:22:46",
        "updated": "2025-10-29 12:22:46"
    },
    {
        "id": 29,
        "title": "dfbdfb",
        "content": "dfdbfb\r\nd\r\n\r\n\r\n\r\n",
        "created": "2025-10-29 12:27:31",
        "updated": "2025-10-29 12:27:31"
    }
]